{
    "ArcherBehavior": {
        "checkpoints": [
            {
                "steps": 50001,
                "file_path": "results/largebatch/ArcherBehavior/ArcherBehavior-50001.onnx",
                "reward": 0.0025637235035670444,
                "creation_time": 1620143263.609531,
                "auxillary_file_paths": [
                    "results/largebatch/ArcherBehavior/ArcherBehavior-50001.pt"
                ]
            }
        ],
        "final_checkpoint": {
            "steps": 50001,
            "file_path": "results/largebatch/ArcherBehavior.onnx",
            "reward": 0.0025637235035670444,
            "creation_time": 1620143263.609531,
            "auxillary_file_paths": [
                "results/largebatch/ArcherBehavior/ArcherBehavior-50001.pt"
            ]
        }
    },
    "metadata": {
        "stats_format_version": "0.3.0",
        "mlagents_version": "0.26.0",
        "torch_version": "1.7.1"
    }
}